crawailer/__init__.py
crawailer/api.py
crawailer/browser.py
crawailer/cli.py
crawailer/config.py
crawailer/content.py
crawailer/mcp.py
crawailer/utils.py
crawailer-0.1.2.dist-info/METADATA
crawailer-0.1.2.dist-info/WHEEL
crawailer-0.1.2.dist-info/entry_points.txt
crawailer-0.1.2.dist-info/licenses/LICENSE
crawailer-0.1.2.dist-info/RECORD
