Metadata-Version: 2.4
Name: crawailer
Version: 0.1.2
Summary: Modern Python library for browser automation and intelligent content extraction with full JavaScript execution support
Project-URL: Homepage, https://git.supported.systems/MCP/crawailer
Project-URL: Repository, https://git.supported.systems/MCP/crawailer
Project-URL: Documentation, https://git.supported.systems/MCP/crawailer/src/branch/main/docs/README.md
Project-URL: Bug Tracker, https://git.supported.systems/MCP/crawailer/issues
Project-URL: Source Code, https://git.supported.systems/MCP/crawailer
Project-URL: API Reference, https://git.supported.systems/MCP/crawailer/src/branch/main/docs/API_REFERENCE.md
Project-URL: JavaScript Guide, https://git.supported.systems/MCP/crawailer/src/branch/main/docs/JAVASCRIPT_API.md
Project-URL: Benchmarks, https://git.supported.systems/MCP/crawailer/src/branch/main/docs/BENCHMARKS.md
Project-URL: Changelog, https://git.supported.systems/MCP/crawailer/releases
Author-email: rpm <hello@crawailer.dev>
Maintainer-email: rpm <hello@crawailer.dev>
License: MIT
License-File: LICENSE
Keywords: ai,angular-scraping,automation,browser-control,content-extraction,javascript-execution,llm,mcp,playwright,react-scraping,spa-crawling,vue-scraping,web-automation,web-scraping
Classifier: Development Status :: 4 - Beta
Classifier: Environment :: Console
Classifier: Framework :: AsyncIO
Classifier: Framework :: Pytest
Classifier: Intended Audience :: Developers
Classifier: Intended Audience :: Information Technology
Classifier: Intended Audience :: Science/Research
Classifier: License :: OSI Approved :: MIT License
Classifier: Operating System :: OS Independent
Classifier: Programming Language :: Python :: 3
Classifier: Programming Language :: Python :: 3 :: Only
Classifier: Programming Language :: Python :: 3.11
Classifier: Programming Language :: Python :: 3.12
Classifier: Programming Language :: Python :: 3.13
Classifier: Topic :: Internet :: WWW/HTTP
Classifier: Topic :: Internet :: WWW/HTTP :: Browsers
Classifier: Topic :: Scientific/Engineering :: Artificial Intelligence
Classifier: Topic :: Scientific/Engineering :: Information Analysis
Classifier: Topic :: Software Development :: Libraries :: Python Modules
Classifier: Topic :: Software Development :: Testing
Classifier: Topic :: Text Processing :: Markup :: HTML
Classifier: Typing :: Typed
Requires-Python: >=3.11
Requires-Dist: anyio>=4.0.0
Requires-Dist: httpx>=0.25.0
Requires-Dist: justext>=3.0.0
Requires-Dist: markdownify>=0.11.6
Requires-Dist: msgpack>=1.0.0
Requires-Dist: playwright>=1.40.0
Requires-Dist: pydantic>=2.0.0
Requires-Dist: rich>=13.0.0
Requires-Dist: selectolax>=0.3.17
Requires-Dist: xxhash>=3.4.0
Provides-Extra: all
Requires-Dist: aiohttp>=3.9.0; extra == 'all'
Requires-Dist: black>=23.0.0; extra == 'all'
Requires-Dist: fastmcp>=0.1.0; extra == 'all'
Requires-Dist: mcp>=0.5.0; extra == 'all'
Requires-Dist: mkdocs-material>=9.0.0; extra == 'all'
Requires-Dist: mkdocs>=1.5.0; extra == 'all'
Requires-Dist: mkdocstrings[python]>=0.20.0; extra == 'all'
Requires-Dist: mypy>=1.5.0; extra == 'all'
Requires-Dist: pre-commit>=3.0.0; extra == 'all'
Requires-Dist: pytest-asyncio>=0.21.0; extra == 'all'
Requires-Dist: pytest-cov>=4.0.0; extra == 'all'
Requires-Dist: pytest-httpserver>=1.0.0; extra == 'all'
Requires-Dist: pytest-mock>=3.10.0; extra == 'all'
Requires-Dist: pytest>=8.0.0; extra == 'all'
Requires-Dist: ruff>=0.1.0; extra == 'all'
Provides-Extra: dev
Requires-Dist: aiohttp>=3.9.0; extra == 'dev'
Requires-Dist: black>=23.0.0; extra == 'dev'
Requires-Dist: mypy>=1.5.0; extra == 'dev'
Requires-Dist: pre-commit>=3.0.0; extra == 'dev'
Requires-Dist: pytest-asyncio>=0.21.0; extra == 'dev'
Requires-Dist: pytest-cov>=4.0.0; extra == 'dev'
Requires-Dist: pytest-httpserver>=1.0.0; extra == 'dev'
Requires-Dist: pytest>=8.0.0; extra == 'dev'
Requires-Dist: ruff>=0.1.0; extra == 'dev'
Provides-Extra: docs
Requires-Dist: mkdocs-material>=9.0.0; extra == 'docs'
Requires-Dist: mkdocs>=1.5.0; extra == 'docs'
Requires-Dist: mkdocstrings[python]>=0.20.0; extra == 'docs'
Provides-Extra: mcp
Requires-Dist: fastmcp>=0.1.0; extra == 'mcp'
Requires-Dist: mcp>=0.5.0; extra == 'mcp'
Provides-Extra: testing
Requires-Dist: aiohttp>=3.9.0; extra == 'testing'
Requires-Dist: pytest-asyncio>=0.21.0; extra == 'testing'
Requires-Dist: pytest-cov>=4.0.0; extra == 'testing'
Requires-Dist: pytest-httpserver>=1.0.0; extra == 'testing'
Requires-Dist: pytest-mock>=3.10.0; extra == 'testing'
Requires-Dist: pytest>=8.0.0; extra == 'testing'
